src/sampei/__init__.py
src/sampei/cli.py
src/sampei/driver.py
src/sampei/masses/__init__.py
src/sampei/masses/calculations.py
src/sampei/masses/masses.py
src/sampei/mgf/MGF.py
src/sampei/mgf/__init__.py
src/sampei/mgf/processer.py
sampei-0.1.2.dist-info/LICENSE
sampei-0.1.2.dist-info/METADATA
sampei-0.1.2.dist-info/WHEEL
sampei-0.1.2.dist-info/entry_points.txt
sampei-0.1.2.dist-info/top_level.txt
sampei-0.1.2.dist-info/RECORD
