Metadata-Version: 2.1
Name: sampei
Version: 0.1.2
Summary: sampei
Home-page: https://github.com/FenyoLab/AgnosticSearch
Author: Zhi Li
Author-email: Zhi.Li@nyulangone.org
License: UNKNOWN
Platform: UNKNOWN
Classifier: Programming Language :: Python :: 3.6
Classifier: License :: OSI Approved :: MIT License
Classifier: Operating System :: MacOS
Classifier: Operating System :: Unix
Requires-Python: >=3.6
License-File: LICENSE
Requires-Dist: numpy (>=1.18.1)
Requires-Dist: pandas (>=1.0.1)
Requires-Dist: pyteomics (>=4.2)
Requires-Dist: numba (>=0.49.0)
